<?xml version="1.0" encoding="iso-8859-1" standalone="no" ?>
<!DOCTYPE phrases SYSTEM "entities.dtd">

<epp:phrases xmlns="http://www.w3.org/1999/xhtml" xmlns:epp="http://eprints.org/ep3/phrase" xmlns:epc="http://eprints.org/ep3/control">

        <epp:phrase id="Plugin/Screen/Admin/StorageManager:title">Storage Manager</epp:phrase>
        <epp:phrase id="Plugin/Screen/Admin/StorageManager:description">Manage your repositories hybrid storage setup, including migration of files.</epp:phrase>

	<epp:phrase id="Plugin/Screen/Admin/StorageManager:store_summary">There are <epc:pin name="total"/> total files stored using this back-end, taking <epc:pin name="human_bytes"/>.</epp:phrase>
	<epp:phrase id="Plugin/Screen/Admin/StorageManager:migrate">Copy to</epp:phrase>
	<epp:phrase id="Plugin/Screen/Admin/StorageManager:delete">Delete Copies</epp:phrase>
        
	<!-- Platforms -->
	
	
	<epp:phrase id="Plugin/Screen/Admin/StorageManager:Storage::HoneyComb">The Honeycomb Platofrm</epp:phrase>
	<epp:phrase id="Plugin/Screen/Admin/StorageManager:Storage::Local">Local Disk Storage</epp:phrase>
	
	<epp:phrase id="Plugin/Screen/Admin/StorageManager:a_local_disk_storage">Local Disk Storage</epp:phrase>
	<epp:phrase id="Plugin/Screen/Admin/StorageManager:a_local_disk_storage_pic"></epp:phrase>
	<epp:phrase id="Plugin/Screen/Admin/StorageManager:m_local_archival_storage">Archival Storage</epp:phrase>
	<epp:phrase id="Plugin/Screen/Admin/StorageManager:m_local_archival_storage_pic"></epp:phrase>
	<epp:phrase id="Plugin/Screen/Admin/StorageManager:z_cloud_storage">Cloud Storage Platforms</epp:phrase>
	<epp:phrase id="Plugin/Screen/Admin/StorageManager:z_cloud_storage_pic"></epp:phrase>


</epp:phrases>
